axolotls/__init__.py
axolotls/column_base.py
axolotls/dtypes.py
axolotls/list_column.py
axolotls/numeric_column.py
axolotls/string_column.py
axolotls/struct_column.py
axolotls/utils.py
axolotls/version.py
axolotls/functional/__init__.py
axolotls/functional/velox.py
axolotls/fx/__init__.py
axolotls/fx/fx_trace.py
axolotls-0.1.0.dev20221017.dist-info/LICENSE
axolotls-0.1.0.dev20221017.dist-info/METADATA
axolotls-0.1.0.dev20221017.dist-info/WHEEL
axolotls-0.1.0.dev20221017.dist-info/top_level.txt
axolotls-0.1.0.dev20221017.dist-info/RECORD
